easysql/__init__.py
easysql/errors.py
easysql/util.py
easysql/queries/__init__.py
easysql/queries/conditions.py
easysql/queries/queries.py
easysql/raw_queries/__init__.py
easysql/raw_queries/common/__init__.py
easysql/raw_queries/common/raw_sql.py
easysql-1.0.1.dist-info/LICENSE
easysql-1.0.1.dist-info/METADATA
easysql-1.0.1.dist-info/WHEEL
easysql-1.0.1.dist-info/top_level.txt
easysql-1.0.1.dist-info/RECORD
