Metadata-Version: 2.1
Name: easysql
Version: 1.0.1
Summary: Python SQL query generator
Home-page: https://github.com/TeamNightSky/EasySQL
Author: TeamNightSky
License: UNKNOWN
Platform: UNKNOWN
Classifier: Development Status :: 2 - Pre-Alpha
Classifier: Operating System :: OS Independent
Classifier: License :: OSI Approved :: Apache Software License
Classifier: Programming Language :: SQL
Classifier: Programming Language :: Python :: 3 :: Only
Classifier: Topic :: Database
Requires-Python: >=3.6
